GaussianCovariance/__init__.py
GaussianCovariance/gaussian_covariance.py
GaussianCovariance-1.0.3.dist-info/LICENSE
GaussianCovariance-1.0.3.dist-info/METADATA
GaussianCovariance-1.0.3.dist-info/WHEEL
GaussianCovariance-1.0.3.dist-info/top_level.txt
GaussianCovariance-1.0.3.dist-info/RECORD
