Metadata-Version: 2.1
Name: GaussianCovariance
Version: 1.0.3
Summary: Python Module to compute the covariance of two-point clustering statistics
Home-page: https://gitlab.com/veropalumbo.alfonso/gaussiancovariance
Author: Alfonso Veropalumbo
Author-email: Alfonso Veropalumbo <alfonso.veropalumbo@inaf.it>, Elena Sarpa <sarpa@cppm.in2p3.fr>
Project-URL: Homepage, https://gitlab.com/veropalumbo.alfonso/gaussiancovariance/
Project-URL: Bug Tracker, https://gitlab.com/veropalumbo.alfonso/gaussiancovariance/issues
Classifier: Programming Language :: Python :: 3
Classifier: License :: OSI Approved :: GNU General Public License v3 or later (GPLv3+)
Classifier: Operating System :: OS Independent
Requires-Python: >=3.6
License-File: LICENSE
Requires-Dist: numpy
Requires-Dist: scipy
